[
  {
    "创新点名称": "双掩码物理模型",
    "创新点工作内容": [
      "设计介质掩码图 $M_{\\text{med}}(x,y)$ 量化像素级粗糙度 $r = a/\\lambda$，区分漫反射（$r \\gg 1$）、镜面反射（$r \\ll 1$）和散射（$r \\approx 1$）",
      "构建角度方向掩码图 $M_{\\text{ang}}(x,y)$ 记录偏折矢量场 $\\Delta\\bm{k}(x,y)$，表征波矢变化",
      "通过物理假设建立反射类型与掩码参数的对应关系（如朗伯场景的介质掩码全域 $r \\gg 1$、角度掩码各向同性）"
    ],
    "创新点价值": "首次统一建模非朗伯场景的深度估计问题，通过双掩码分离材质特性与几何信息，解决传统EPI方法对非朗伯反射的失效问题",
    "支撑证据": "当前基线在Non-Lambertian场景MAE为0.411，需通过双掩码模型显著降低；Phase 3目标要求Non-Lambertian MAE <0.25"
  },
  {
    "创新点名称": "类MRI角度频率分析",
    "创新点工作内容": [
      "对光场的9×9角度采样进行2D-FFT，通过频谱能量分布进行材质分类（漫反射低频主导、镜面高频展宽、散射中频为主）",
      "设计分层解析框架：第一层轻量级角度频谱分类（复杂度$O(HW)$），第二层BRDF参数估计，第三层完整物理建模",
      "建立MRI类比分析框架，将角度编码比作MRI的梯度磁场，角度频谱对应组织分类的T1/T2弛豫差异分析"
    ],
    "创新点价值": "首次将医学影像的频域分析思想引入光场材质分析，实现材质类型的实时粗粒度分类，为后续深度估计提供先验指导",
    "支撑证据": "Phase 1验证计划要求三分类准确率>85%，且直方图验证角度频谱分布可分性；现有基线在Non-Lambertian场景失效源于缺乏材质感知"
  },
  {
    "创新点名称": "分量感知深度估计策略",
    "创新点工作内容": [
      "根据介质掩码权重动态选择深度估计方法：漫反射区用EPI、镜面区用光度立体、散射区用散射模型修正",
      "设计加权融合机制 $D = w_d D_{\\text{EPI}} + w_s D_{\\text{specular}} + w_{sc} D_{\\text{scatter}}$",
      "在损失函数中引入介质掩码置信度加权，提升混合场景的深度估计鲁棒性"
    ],
    "创新点价值": "突破传统方法全域假设的局限性，通过材质感知的动态策略显著提升非朗伯场景的深度估计精度",
    "支撑证据": "当前基线在Mixed场景MAE为0.081（接近目标），但Non-Lambertian场景完全失效；Phase 3目标要求Non-Lambertian MAE从0.411显著下降"
  }
]